{"is_source_file": true, "format": "Kotlin", "description": "MainActivity class implementation for an Android app handling authentication, biometric unlock, and UI rendering based on app state.", "external_files": ["R.layout.activity_main", "R.layout.screen_login", "R.layout.screen_locked", "R.layout.screen_main", "org.example.app.auth.BiometricAuth", "org.example.app.lock.AppLockObserver", "android.os.Bundle", "android.view.LayoutInflater", "android.view.View", "android.widget.Button", "android.widget.EditText", "android.widget.TextView", "androidx.appcompat.app.AppCompatActivity", "androidx.lifecycle.ProcessLifecycleOwner", "androidx.lifecycle.lifecycleScope"], "external_methods": ["androidx.lifecycle.ProcessLifecycleOwner.get", "androidx.lifecycle.Lifecycle.addObserver", "androidx.core.view.LayoutInflater.from", "android.view.LayoutInflater.inflate", "android.widget.FrameLayout.removeAllViews", "android.widget.FrameLayout.addView", "android.widget.Button.setOnClickListener", "android.widget.EditText.setEnabled", "android.widget.TextView.setText", "androidx.lifecycle.lifecycleScope.launch", "org.example.app.auth.BiometricAuth.canAuthenticate", "org.example.app.auth.BiometricAuth.authenticate", "org.example.app.auth.BiometricAuth.onSuccess", "org.example.app.auth.BiometricAuth.onError", "org.example.app.auth.authManager.login", "org.example.app.auth.authManager.logout", "org.example.app.auth.authManager.currentTokens", "org.example.app.auth.authManager.unlockApp", "org.example.app.getOrCreateApiClient", "apiClient.service.get"], "published": ["MainActivity"], "classes": [{"name": "MainActivity", "description": "An activity managing app lifecycle, authentication states, biometric unlock, and dynamic UI rendering."}], "methods": [{"name": "onCreate", "description": "Initializes activity, sets content view, adds lifecycle observer, and calls render."}, {"name": "onResume", "description": "Re-renders UI when activity resumes to reflect current state."}, {"name": "render", "description": "Determines current app state and displays corresponding UI or error message."}, {"name": "showInitFailure", "description": "Displays an error screen if application failed to initialize."}, {"name": "showLogin", "description": "Displays login UI and handles login button click to attempt user login."}, {"name": "showLocked", "description": "Displays biometric unlock screen and handles biometric authentication."}, {"name": "showMain", "description": "Displays main app UI with session info, API call button, and logout button."}, {"name": "setRoot", "description": "Replaces current root view with a new view."}], "calls": ["ProcessLifecycleOwner.get().lifecycle.addObserver", "LayoutInflater.from(this).inflate", "findViewById", "lifecycleScope.launch", "app.authManager.login", "app.authManager.logout", "BiometricAuth.canAuthenticate", "BiometricAuth.authenticate", "app.authManager.unlockApp", "app.getOrCreateApiClient", "apiClient.service.get"], "search-terms": ["MainActivity Kotlin", "Biometric Authentication", "App Lifecycle Observer", "UI Rendering", "Authentication Flow", "API Client Interaction", "Android View Inflation", "Lifecycle-aware UI"], "state": 2, "file_id": 19, "knowledge_revision": 52, "git_revision": "649d6a026faace7091176f98e7eee946be6d5a1c", "revision_history": [{"41": ""}, {"45": ""}, {"49": "4e4daece06bae5965c978a9521fa5c42e20e8b72"}, {"52": "649d6a026faace7091176f98e7eee946be6d5a1c"}], "hash": "63493149e1f44e23fd89f62f24c63a37", "format-version": 4, "code-base-name": "android_kotlin_frontend", "filename": "android_kotlin_frontend/app/src/main/kotlin/org/example/app/MainActivity.kt"}